<tgcScene>
	<name>Puerta</name>
	<texturesExport enabled='true' dir='Textures'/>
	<lightmapExport enabled='false' dir='LightMaps'/>
	<sceneBoundingBox min='[-8.65697,0.0729866,-1.18024]' max='[8.65696,46.2312,1.18026]'/>
	<materials count='1'>
		<m name='Material #1' type='Standardmaterial'>
			<ambient>[149.94,149.94,149.94,255.0]</ambient>
			<diffuse>[149.94,149.94,149.94,255.0]</diffuse>
			<specular>[229.5,229.5,229.5,255.0]</specular>
			<opacity>100.0</opacity>
			<alphaBlendEnable>false</alphaBlendEnable>
			<bitmap uvTiling='[1.0,1.0]' uvOffset='[0.0,0.0]'>Puerta.jpg</bitmap>
		</m>
	</materials>
	<meshes count='1' >
		<mesh name='Puerta' layer='0' type='Original' matId='0' color='[27.0,177.0,27.0]' visibility='1.0' lightmap=''>
			<boundingBox min='[-8.65697,0.0729866,-1.18024]' max='[8.65696,46.2312,1.18026]'/>
			<coordinatesIdx count='36'>0 2 3 3 1 0 4 5 7 7 6 4 0 1 5 5 4 0 1 3 7 7 5 1 3 2 6 6 7 3 2 0 4 4 6 2 </coordinatesIdx>
			<textCoordsIdx count='36'>0 2 3 3 1 0 4 5 7 7 6 4 8 9 10 10 11 8 12 13 14 14 15 12 16 17 18 18 19 16 20 21 22 22 23 20 </textCoordsIdx>
			<colorsIdx count='36'>0 0 0 0 0 0 0 0 0 0 0 0 0 0 0 0 0 0 0 0 0 0 0 0 0 0 0 0 0 0 0 0 0 0 0 0 </colorsIdx>
			<matIds count='1'>0</matIds>
			<vertices count='24'>-8.65697 0.0759869 1.17846 -8.65695 0.0759869 -1.18024 -8.64931 46.2312 1.17846 -8.64929 46.2312 -1.18024 8.64928 0.0729866 1.18026 8.6493 0.0729866 -1.17844 8.65694 46.2282 1.18026 8.65696 46.2282 -1.17844 </vertices>
			<normals count='108'>-1.0 0.000165858 0.0 -1.0 0.000165858 0.0 -1.0 0.000165858 0.0 -1.0 0.000165858 0.0 -1.0 0.000165858 0.0 -1.0 0.000165858 0.0 1.0 -0.000165873 0.0 1.0 -0.000165872 0.0 1.0 -0.0001659 0.0 1.0 -0.0001659 0.0 1.0 -0.000165901 0.0 1.0 -0.000165873 0.0 -0.000173302 -1.0 0.0 -0.000173302 -1.0 0.0 -0.000173302 -1.0 0.0 -0.000173302 -1.0 0.0 -0.000173302 -1.0 0.0 -0.000173302 -1.0 0.0 0.00010403 0.0 -1.0 0.000104033 0.0 -1.0 0.000104032 0.0 -1.0 0.000104032 0.0 -1.0 0.000104029 0.0 -1.0 0.00010403 0.0 -1.0 0.000172916 1.0 0.0 0.000172916 1.0 0.0 0.000172916 1.0 0.0 0.000172916 1.0 0.0 0.000172916 1.0 0.0 0.000172916 1.0 0.0 -0.000104066 0.0 1.0 -0.000104062 0.0 1.0 -0.000104063 0.0 1.0 -0.000104063 0.0 1.0 -0.000104067 0.0 1.0 -0.000104066 0.0 1.0 </normals>
			<texCoords count='48'>0.840253 0.926812 0.79335 0.928781 0.801931 -0.00551486 0.755028 -0.0035454 0.14547 0.923289 0.192373 0.925258 0.183792 -0.00903821 0.230695 -0.00706863 0.840253 0.0124981 0.79335 0.0182197 0.807627 1.02411 0.85453 1.01839 0.98178 0.928781 1.0042 -0.0035454 -0.00169277 -0.00706863 -0.0241102 0.925258 0.244972 -0.00419784 0.198069 -0.0099194 0.183792 0.995971 0.230695 1.00169 -0.00991935 -0.00551486 0.0124982 0.926812 1.01839 0.923289 0.995971 -0.00903821 </texCoords>
			<colors count='3'>255 255 255 </colors>
		</mesh>
	</meshes>
</tgcScene>
