<tgcScene>
	<name>Mesa</name>
	<texturesExport enabled='true' dir='Textures'/>
	<lightmapExport enabled='false' dir='LightMaps'/>
	<sceneBoundingBox min='[-47.7319,0.102725,-22.6004]' max='[47.7319,30.0434,22.6004]'/>
	<materials count='1'>
		<m name='Material #26' type='Standardmaterial'>
			<ambient>[149.94,149.94,149.94,255.0]</ambient>
			<diffuse>[149.94,149.94,149.94,255.0]</diffuse>
			<specular>[229.5,229.5,229.5,255.0]</specular>
			<opacity>100.0</opacity>
			<alphaBlendEnable>false</alphaBlendEnable>
			<bitmap uvTiling='[1.0,1.0]' uvOffset='[0.0,0.0]'>table.jpg</bitmap>
		</m>
	</materials>
	<meshes count='1' >
		<mesh name='Mesa' layer='0' type='Original' matId='0' color='[134.0,6.0,6.0]' visibility='1.0' lightmap=''>
			<boundingBox min='[-47.7319,0.102725,-22.6004]' max='[47.7319,30.0434,22.6004]'/>
			<coordinatesIdx count='300'>14 17 19 14 19 1 14 1 0 15 14 0 18 29 28 18 28 2 18 2 1 19 18 1 27 26 25 27 25 3 27 3 2 28 27 2 25 24 16 16 15 0 25 16 0 3 25 0 22 23 30 30 31 21 21 20 12 30 21 12 22 30 12 13 22 12 4 7 3 3 0 4 5 4 0 0 1 5 6 5 1 1 2 6 7 6 2 2 3 7 8 11 7 7 4 8 9 8 4 4 5 9 10 9 5 5 6 10 11 10 6 6 7 11 10 11 8 8 9 10 12 14 16 16 13 12 16 24 22 22 13 16 15 16 14 17 18 19 21 31 29 29 18 21 17 14 12 12 20 17 18 17 20 20 21 18 24 26 23 23 22 24 26 27 30 30 23 26 26 24 25 28 29 27 30 27 29 29 31 30 35 34 33 33 32 35 36 39 35 35 32 36 37 36 32 32 33 37 39 38 34 34 35 39 38 39 36 36 37 38 43 42 41 41 40 43 44 47 43 43 40 44 45 44 40 40 41 45 47 46 42 42 43 47 46 47 44 44 45 46 51 50 49 49 48 51 52 55 51 51 48 52 53 52 48 48 49 53 55 54 50 50 51 55 54 55 52 52 53 54 59 58 57 57 56 59 60 63 59 59 56 60 61 60 56 56 57 61 63 62 58 58 59 63 62 63 60 60 61 62 </coordinatesIdx>
			<textCoordsIdx count='300'>19 27 31 19 31 1 19 1 0 21 19 0 30 56 54 30 54 2 30 2 1 31 30 1 52 48 47 52 47 3 52 3 2 54 52 2 47 44 22 22 21 0 47 22 0 3 47 0 40 43 60 60 63 37 37 34 14 60 37 14 40 60 14 17 40 14 4 7 3 3 0 4 5 4 0 0 1 5 6 5 1 1 2 6 7 6 2 2 3 7 8 11 7 7 4 8 9 8 4 4 5 9 10 9 5 5 6 10 11 10 6 6 7 11 10 11 8 8 9 10 13 20 24 24 16 13 23 46 39 39 15 23 21 22 19 27 30 31 36 62 57 57 29 36 26 18 12 12 33 26 28 25 32 32 35 28 45 50 42 42 38 45 49 53 59 59 41 49 48 44 47 54 56 52 58 51 55 55 61 58 71 68 66 66 64 71 73 77 70 70 65 73 74 72 64 64 66 74 76 75 67 67 69 76 75 76 72 72 74 75 84 83 82 82 80 84 87 91 85 85 79 87 88 86 78 78 81 88 90 89 83 83 84 90 89 90 86 86 88 89 96 95 94 94 92 96 99 105 97 97 93 99 100 98 92 92 94 100 104 102 95 95 96 104 101 103 98 98 100 101 110 109 108 108 106 110 114 119 111 111 107 114 116 113 106 106 108 116 118 117 109 109 110 118 117 118 112 112 115 117 </textCoordsIdx>
			<colorsIdx count='300'>0 0 0 0 0 0 0 0 0 0 0 0 0 0 0 0 0 0 0 0 0 0 0 0 0 0 0 0 0 0 0 0 0 0 0 0 0 0 0 0 0 0 0 0 0 0 0 0 0 0 0 0 0 0 0 0 0 0 0 0 0 0 0 0 0 0 0 0 0 0 0 0 0 0 0 0 0 0 0 0 0 0 0 0 0 0 0 0 0 0 0 0 0 0 0 0 0 0 0 0 0 0 0 0 0 0 0 0 0 0 0 0 0 0 0 0 0 0 0 0 0 0 0 0 0 0 0 0 0 0 0 0 0 0 0 0 0 0 0 0 0 0 0 0 0 0 0 0 0 0 0 0 0 0 0 0 0 0 0 0 0 0 0 0 0 0 0 0 0 0 0 0 0 0 0 0 0 0 0 0 0 0 0 0 0 0 0 0 0 0 0 0 0 0 0 0 0 0 0 0 0 0 0 0 0 0 0 0 0 0 0 0 0 0 0 0 0 0 0 0 0 0 0 0 0 0 0 0 0 0 0 0 0 0 0 0 0 0 0 0 0 0 0 0 0 0 0 0 0 0 0 0 0 0 0 0 0 0 0 0 0 0 0 0 0 0 0 0 0 0 0 0 0 0 0 0 0 0 0 0 0 0 0 0 0 0 0 0 0 0 0 0 0 0 0 0 0 0 0 0 </colorsIdx>
			<matIds count='1'>0</matIds>
			<vertices count='192'>-45.9239 29.3604 -20.7923 45.9239 29.3604 -20.7923 45.9239 29.3604 20.7923 -45.9239 29.3604 20.7923 -45.9239 29.5211 -20.7923 45.9239 29.5211 -20.7923 45.9239 29.5211 20.7923 -45.9239 29.5211 20.7923 -45.4016 30.0434 -20.27 45.4016 30.0434 -20.27 45.4016 30.0434 20.27 -45.4016 30.0434 20.27 -45.6427 26.6483 -22.6004 -47.7319 26.6483 -20.5111 -45.6427 29.3604 -22.6004 -46.2546 29.3604 -21.123 -47.7319 29.3604 -20.5111 45.6427 29.3604 -22.6004 47.7319 29.3604 -20.5111 46.2546 29.3604 -21.123 45.6427 26.6483 -22.6004 47.7319 26.6483 -20.5111 -47.7319 26.6483 20.5111 -45.6427 26.6483 22.6004 -47.7319 29.3604 20.5111 -46.2546 29.3604 21.123 -45.6427 29.3604 22.6004 45.6427 29.3604 22.6004 46.2546 29.3604 21.123 47.7319 29.3604 20.5111 45.6427 26.6483 22.6004 47.7319 26.6483 20.5111 -43.4469 0.102725 14.8295 -43.4469 28.2954 14.8295 -39.147 28.2954 14.8295 -39.147 0.102725 14.8295 -43.4469 0.102725 19.1293 -43.4469 28.2954 19.1293 -39.147 28.2954 19.1293 -39.147 0.102725 19.1293 39.1728 0.102725 14.8295 39.1728 28.2954 14.8295 43.4726 28.2954 14.8295 43.4726 0.102725 14.8295 39.1728 0.102725 19.1293 39.1728 28.2954 19.1293 43.4726 28.2954 19.1293 43.4726 0.102725 19.1293 -43.4469 0.102725 -19.4218 -43.4469 28.2954 -19.4218 -39.147 28.2954 -19.4218 -39.147 0.102725 -19.4218 -43.4469 0.102725 -15.122 -43.4469 28.2954 -15.122 -39.147 28.2954 -15.122 -39.147 0.102725 -15.122 39.1728 0.102725 -19.4218 39.1728 28.2954 -19.4218 43.4726 28.2954 -19.4218 43.4726 0.102725 -19.4218 39.1728 0.102725 -15.122 39.1728 28.2954 -15.122 43.4726 28.2954 -15.122 43.4726 0.102725 -15.122 </vertices>
			<normals count='900'>-0.297109 0.630262 -0.717284 0.297109 0.630262 -0.717283 0.0 1.0 0.0 -0.297109 0.630262 -0.717284 0.0 1.0 0.0 0.301511 0.904534 -0.301511 -0.297109 0.630262 -0.717284 0.301511 0.904534 -0.301511 -0.301511 0.904534 -0.301511 0.0 1.0 0.0 -0.297109 0.630262 -0.717284 -0.301511 0.904534 -0.301511 0.717285 0.630261 -0.297108 0.717284 0.630263 0.297108 0.0 1.0 0.0 0.717285 0.630261 -0.297108 0.0 1.0 0.0 0.301511 0.904534 0.301511 0.717285 0.630261 -0.297108 0.301511 0.904534 0.301511 0.301511 0.904534 -0.301511 0.0 1.0 0.0 0.717285 0.630261 -0.297108 0.301511 0.904534 -0.301511 0.297109 0.630262 0.717284 -0.297109 0.630262 0.717283 0.0 1.0 0.0 0.297109 0.630262 0.717284 0.0 1.0 0.0 -0.301511 0.904534 0.301511 0.297109 0.630262 0.717284 -0.301511 0.904534 0.301511 0.301511 0.904534 0.301511 0.0 1.0 0.0 0.297109 0.630262 0.717284 0.301511 0.904534 0.301511 0.0 1.0 0.0 -0.717284 0.630263 0.297108 -0.717284 0.630263 -0.297108 -0.717284 0.630263 -0.297108 0.0 1.0 0.0 -0.301511 0.904534 -0.301511 0.0 1.0 0.0 -0.717284 0.630263 -0.297108 -0.301511 0.904534 -0.301511 -0.301511 0.904534 0.301511 0.0 1.0 0.0 -0.301511 0.904534 -0.301511 -0.717284 -0.630262 0.297108 -0.297109 -0.630262 0.717283 0.297109 -0.630262 0.717283 0.297109 -0.630262 0.717283 0.717284 -0.630263 0.297108 0.717284 -0.630263 -0.297108 0.717284 -0.630263 -0.297108 0.297109 -0.630262 -0.717283 -0.297109 -0.630263 -0.717283 0.297109 -0.630262 0.717283 0.717284 -0.630263 -0.297108 -0.297109 -0.630263 -0.717283 -0.717284 -0.630262 0.297108 0.297109 -0.630262 0.717283 -0.297109 -0.630263 -0.717283 -0.717284 -0.630263 -0.297108 -0.717284 -0.630262 0.297108 -0.297109 -0.630263 -0.717283 -0.650705 0.391362 -0.650706 -0.650706 0.391362 0.650706 -0.301511 0.904534 0.301511 -0.301511 0.904534 0.301511 -0.301511 0.904534 -0.301511 -0.650705 0.391362 -0.650706 0.650706 0.391362 -0.650706 -0.650705 0.391362 -0.650706 -0.301511 0.904534 -0.301511 -0.301511 0.904534 -0.301511 0.301511 0.904534 -0.301511 0.650706 0.391362 -0.650706 0.650705 0.391362 0.650706 0.650706 0.391362 -0.650706 0.301511 0.904534 -0.301511 0.301511 0.904534 -0.301511 0.301511 0.904534 0.301511 0.650705 0.391362 0.650706 -0.650706 0.391362 0.650706 0.650705 0.391362 0.650706 0.301511 0.904534 0.301511 0.301511 0.904534 0.301511 -0.301511 0.904534 0.301511 -0.650706 0.391362 0.650706 -0.300194 0.90541 -0.300193 -0.300194 0.90541 0.300192 -0.650706 0.391362 0.650706 -0.650706 0.391362 0.650706 -0.650705 0.391362 -0.650706 -0.300194 0.90541 -0.300193 0.300194 0.90541 -0.300192 -0.300194 0.90541 -0.300193 -0.650705 0.391362 -0.650706 -0.650705 0.391362 -0.650706 0.650706 0.391362 -0.650706 0.300194 0.90541 -0.300192 0.300194 0.90541 0.300193 0.300194 0.90541 -0.300192 0.650706 0.391362 -0.650706 0.650706 0.391362 -0.650706 0.650705 0.391362 0.650706 0.300194 0.90541 0.300193 -0.300194 0.90541 0.300192 0.300194 0.90541 0.300193 0.650705 0.391362 0.650706 0.650705 0.391362 0.650706 -0.650706 0.391362 0.650706 -0.300194 0.90541 0.300192 0.300194 0.90541 0.300193 -0.300194 0.90541 0.300192 -0.300194 0.90541 -0.300193 -0.300194 0.90541 -0.300193 0.300194 0.90541 -0.300192 0.300194 0.90541 0.300193 -0.297109 -0.630263 -0.717283 -0.297109 0.630262 -0.717284 -0.717284 0.630263 -0.297108 -0.717284 0.630263 -0.297108 -0.717284 -0.630263 -0.297108 -0.297109 -0.630263 -0.717283 -0.717284 0.630263 -0.297108 -0.717284 0.630263 0.297108 -0.717284 -0.630262 0.297108 -0.717284 -0.630262 0.297108 -0.717284 -0.630263 -0.297108 -0.717284 0.630263 -0.297108 0.0 1.0 0.0 -0.717284 0.630263 -0.297108 -0.297109 0.630262 -0.717284 0.297109 0.630262 -0.717283 0.717285 0.630261 -0.297108 0.0 1.0 0.0 0.717284 -0.630263 -0.297108 0.717284 -0.630263 0.297108 0.717284 0.630263 0.297108 0.717284 0.630263 0.297108 0.717285 0.630261 -0.297108 0.717284 -0.630263 -0.297108 0.297109 0.630262 -0.717283 -0.297109 0.630262 -0.717284 -0.297109 -0.630263 -0.717283 -0.297109 -0.630263 -0.717283 0.297109 -0.630262 -0.717283 0.297109 0.630262 -0.717283 0.717285 0.630261 -0.297108 0.297109 0.630262 -0.717283 0.297109 -0.630262 -0.717283 0.297109 -0.630262 -0.717283 0.717284 -0.630263 -0.297108 0.717285 0.630261 -0.297108 -0.717284 0.630263 0.297108 -0.297109 0.630262 0.717283 -0.297109 -0.630262 0.717283 -0.297109 -0.630262 0.717283 -0.717284 -0.630262 0.297108 -0.717284 0.630263 0.297108 -0.297109 0.630262 0.717283 0.297109 0.630262 0.717284 0.297109 -0.630262 0.717283 0.297109 -0.630262 0.717283 -0.297109 -0.630262 0.717283 -0.297109 0.630262 0.717283 -0.297109 0.630262 0.717283 -0.717284 0.630263 0.297108 0.0 1.0 0.0 0.0 1.0 0.0 0.717284 0.630263 0.297108 0.297109 0.630262 0.717284 0.297109 -0.630262 0.717283 0.297109 0.630262 0.717284 0.717284 0.630263 0.297108 0.717284 0.630263 0.297108 0.717284 -0.630263 0.297108 0.297109 -0.630262 0.717283 0.57735 -0.57735 -0.57735 0.707107 0.0 -0.707107 -0.707107 0.0 -0.707107 -0.707107 0.0 -0.707107 -0.57735 -0.57735 -0.57735 0.57735 -0.57735 -0.57735 -0.57735 -0.57735 0.57735 0.57735 -0.57735 0.57735 0.57735 -0.57735 -0.57735 0.57735 -0.57735 -0.57735 -0.57735 -0.57735 -0.57735 -0.57735 -0.57735 0.57735 -0.707107 0.0 0.707107 -0.57735 -0.57735 0.57735 -0.57735 -0.57735 -0.57735 -0.57735 -0.57735 -0.57735 -0.707107 0.0 -0.707107 -0.707107 0.0 0.707107 0.57735 -0.57735 0.57735 0.707107 0.0 0.707107 0.707107 0.0 -0.707107 0.707107 0.0 -0.707107 0.57735 -0.57735 -0.57735 0.57735 -0.57735 0.57735 0.707107 0.0 0.707107 0.57735 -0.57735 0.57735 -0.57735 -0.57735 0.57735 -0.57735 -0.57735 0.57735 -0.707107 0.0 0.707107 0.707107 0.0 0.707107 0.57735 -0.57735 -0.57735 0.707107 0.0 -0.707107 -0.707107 0.0 -0.707107 -0.707107 0.0 -0.707107 -0.57735 -0.57735 -0.57735 0.57735 -0.57735 -0.57735 -0.57735 -0.57735 0.57735 0.57735 -0.57735 0.57735 0.57735 -0.57735 -0.57735 0.57735 -0.57735 -0.57735 -0.57735 -0.57735 -0.57735 -0.57735 -0.57735 0.57735 -0.707107 0.0 0.707107 -0.57735 -0.57735 0.57735 -0.57735 -0.57735 -0.57735 -0.57735 -0.57735 -0.57735 -0.707107 0.0 -0.707107 -0.707107 0.0 0.707107 0.57735 -0.57735 0.57735 0.707107 0.0 0.707107 0.707107 0.0 -0.707107 0.707107 0.0 -0.707107 0.57735 -0.57735 -0.57735 0.57735 -0.57735 0.57735 0.707107 0.0 0.707107 0.57735 -0.57735 0.57735 -0.57735 -0.57735 0.57735 -0.57735 -0.57735 0.57735 -0.707107 0.0 0.707107 0.707107 0.0 0.707107 0.57735 -0.57735 -0.57735 0.707107 0.0 -0.707107 -0.707107 0.0 -0.707107 -0.707107 0.0 -0.707107 -0.57735 -0.57735 -0.57735 0.57735 -0.57735 -0.57735 -0.57735 -0.57735 0.57735 0.57735 -0.57735 0.57735 0.57735 -0.57735 -0.57735 0.57735 -0.57735 -0.57735 -0.57735 -0.57735 -0.57735 -0.57735 -0.57735 0.57735 -0.707107 0.0 0.707107 -0.57735 -0.57735 0.57735 -0.57735 -0.57735 -0.57735 -0.57735 -0.57735 -0.57735 -0.707107 0.0 -0.707107 -0.707107 0.0 0.707107 0.57735 -0.57735 0.57735 0.707107 0.0 0.707107 0.707107 0.0 -0.707107 0.707107 0.0 -0.707107 0.57735 -0.57735 -0.57735 0.57735 -0.57735 0.57735 0.707107 0.0 0.707107 0.57735 -0.57735 0.57735 -0.57735 -0.57735 0.57735 -0.57735 -0.57735 0.57735 -0.707107 0.0 0.707107 0.707107 0.0 0.707107 0.57735 -0.57735 -0.57735 0.707107 0.0 -0.707107 -0.707107 0.0 -0.707107 -0.707107 0.0 -0.707107 -0.57735 -0.57735 -0.57735 0.57735 -0.57735 -0.57735 -0.57735 -0.57735 0.57735 0.57735 -0.57735 0.57735 0.57735 -0.57735 -0.57735 0.57735 -0.57735 -0.57735 -0.57735 -0.57735 -0.57735 -0.57735 -0.57735 0.57735 -0.707107 0.0 0.707107 -0.57735 -0.57735 0.57735 -0.57735 -0.57735 -0.57735 -0.57735 -0.57735 -0.57735 -0.707107 0.0 -0.707107 -0.707107 0.0 0.707107 0.57735 -0.57735 0.57735 0.707107 0.0 0.707107 0.707107 0.0 -0.707107 0.707107 0.0 -0.707107 0.57735 -0.57735 -0.57735 0.57735 -0.57735 0.57735 0.707107 0.0 0.707107 0.57735 -0.57735 0.57735 -0.57735 -0.57735 0.57735 -0.57735 -0.57735 0.57735 -0.707107 0.0 0.707107 0.707107 0.0 0.707107 </normals>
			<texCoords count='240'>0.036258 0.97322 0.963742 0.97322 0.963742 0.553295 0.036258 0.553295 0.036258 0.97322 0.963742 0.97322 0.963742 0.553295 0.036258 0.553295 0.041532 0.967945 0.958468 0.967945 0.958468 0.55857 0.041532 0.55857 0.99082 0.50293 0.943072 0.051519 0.404028 0.527136 0.696669 0.407229 0.906248 0.051519 0.412872 0.518292 0.99082 0.519897 0.039098 0.991477 0.943072 0.01772 0.032918 0.976559 0.018 0.97038 0.696669 0.426124 0.906248 0.01772 0.849806 0.017543 0.419692 0.519897 0.960902 0.991477 0.886629 0.017543 0.988031 0.462898 0.982 0.97038 0.967082 0.976559 0.849806 0.051342 0.419692 0.50293 0.017616 0.527136 0.886629 0.051342 0.988031 0.444003 0.008772 0.518292 0.943086 0.10158 0.982477 0.407229 0.412872 0.344645 0.41998 0.475728 0.906262 0.10158 0.404028 0.335801 0.018 0.556136 0.943086 0.067781 0.982477 0.426124 0.032918 0.549956 0.039098 0.535038 0.41998 0.492696 0.906262 0.067781 0.886059 0.067954 0.960902 0.535038 0.991108 0.492696 0.967082 0.549956 0.849235 0.067954 0.982 0.556136 0.702223 0.462898 0.886059 0.101753 0.991108 0.475728 0.017616 0.335801 0.849235 0.101753 0.702223 0.444003 0.008772 0.344645 0.678663 0.00876701 0.606077 0.462978 0.678663 0.330767 0.825994 0.330767 0.629552 0.330767 0.825994 0.00876701 0.552489 0.462978 0.629552 0.00876701 0.727773 0.00876701 0.606077 0.409389 0.727773 0.330767 0.776883 0.330767 0.776883 0.00876701 0.552489 0.409389 0.205093 0.330256 0.677449 0.462715 0.008652 0.330256 0.205093 0.00825602 0.008652 0.00825602 0.057762 0.00825602 0.057762 0.330256 0.623861 0.462715 0.155983 0.330256 0.677449 0.409127 0.155983 0.00825602 0.106872 0.00825602 0.106872 0.330256 0.623861 0.409127 0.315306 0.00775599 0.604573 0.400615 0.315306 0.329756 0.266195 0.329756 0.266195 0.00775599 0.550985 0.400615 0.364416 0.00775599 0.604573 0.347027 0.364416 0.329756 0.413527 0.329756 0.217085 0.329756 0.413527 0.00775599 0.217085 0.00775599 0.550985 0.347027 0.568483 0.00891101 0.674002 0.400353 0.568483 0.330911 0.519373 0.330911 0.519373 0.00891101 0.620413 0.400353 0.421152 0.00891101 0.617594 0.00891101 0.674002 0.346765 0.421152 0.330911 0.617594 0.330911 0.470262 0.330911 0.470262 0.00891101 0.620413 0.346765 </texCoords>
			<colors count='3'>255 255 255 </colors>
		</mesh>
	</meshes>
</tgcScene>
